nanoaccelerate/__init__.py
nanoaccelerate-0.0.0a0.dist-info/METADATA
nanoaccelerate-0.0.0a0.dist-info/WHEEL
nanoaccelerate-0.0.0a0.dist-info/top_level.txt
nanoaccelerate-0.0.0a0.dist-info/RECORD
