Metadata-Version: 2.4
Name: nanoaccelerate
Version: 0.0.0a0
Summary: mini-accelerate
Home-page: https://github.com/muellerzr/nanoaccelerate
Author: Zach Mueller
Author-email: walkwithcode@gmail.com
License: Apache
Keywords: deep learning
Classifier: Development Status :: 2 - Pre-Alpha
Classifier: Intended Audience :: Developers
Classifier: Intended Audience :: Education
Classifier: Intended Audience :: Science/Research
Classifier: License :: OSI Approved :: Apache Software License
Classifier: Operating System :: OS Independent
Classifier: Programming Language :: Python :: 3
Classifier: Programming Language :: Python :: 3.9
Classifier: Topic :: Scientific/Engineering :: Artificial Intelligence
Requires-Python: >=3.9.0
Requires-Dist: numpy<3.0.0,>=1.17
Requires-Dist: packaging>=20.0
Requires-Dist: psutil
Requires-Dist: pyyaml
Requires-Dist: torch>=2.0.0
Requires-Dist: huggingface_hub>=0.21.0
Requires-Dist: safetensors>=0.4.3
Provides-Extra: quality
Requires-Dist: black~=23.1; extra == "quality"
Requires-Dist: ruff~=0.11.2; extra == "quality"
Dynamic: author
Dynamic: author-email
Dynamic: classifier
Dynamic: description-content-type
Dynamic: home-page
Dynamic: keywords
Dynamic: license
Dynamic: provides-extra
Dynamic: requires-dist
Dynamic: requires-python
Dynamic: summary
